sqla_filter/__init__.py
sqla_filter/base.py
sqla_filter/filter_.py
sqla_filter/ordering.py
sqla_filter/py.typed
sqla_filter/relationship.py
sqla_filter/types_.py
sqla_filter/unset.py
sqla_filter-0.5.7.dist-info/METADATA
sqla_filter-0.5.7.dist-info/WHEEL
sqla_filter-0.5.7.dist-info/RECORD
